{
    "title": "Easiest way to find words with letters in certain positions - Wordswithletters",
    "h1": "Find words with letters in certain positions",
    "h2": "Enter letters at given positions below and submit",
    "meta": "Enter letters at specific positions, press submit, and that's all you need to do to find words ",
    "tags": "",
    "categories": "wordle",
    "featureNo": "02",
    "feature_title": "Features",
    "featureList": [
        {
            "feature_heading": "",
            "feature_text": "",
            "fa_class": "../assets/images/star.svg"
        },
        {
            "feature_heading": "",
            "feature_text": "",
            "fa_class": "../assets/images/star.svg"
        },
        {
            "feature_heading": "",
            "feature_text": "",
            "fa_class": "../assets/images/star.svg"
        },
        {
            "feature_heading": "",
            "feature_text": "",
            "fa_class": "../assets/images/star.svg"
        },
        {
            "feature_heading": "",
            "feature_text": "",
            "fa_class": "../assets/images/star.svg"
        },
        {
            "feature_heading": "",
            "feature_text": "",
            "fa_class": "../assets/images/star.svg"
        }
    ],
    "HOW_TO_CONTENT": {
        "logoImageUrl": "https://smallpdf.com/build/73d77e3d204fd7defc9de80bf83fcbeb.svg",
        "heading": "How to set alarm for $variable minutes:",
        "steps": [
            "Click on set alarm ",
            "Set $variable minutes for alarm.",
            "Choose sound of your choice.",
            "Click submit to set alarm, that's it !."
        ]
    },
    "faqList": [
        {
            "Question": "",
            "Answer": ""
        }
    ],
    "jsfilepaths": [
        "../assets/js/words-in-certain-positions.js"
    ],
    "cssfilepaths": [
        "../assets/css/wordsInCertainPosition.css"
    ]
}